bolig_ping/__init__.py
bolig_ping/cache.py
bolig_ping/cli.py
bolig_ping/data_models.py
bolig_ping/email.py
bolig_ping/filtering.py
bolig_ping/scraper.py
bolig_ping-1.6.1.dist-info/METADATA
bolig_ping-1.6.1.dist-info/WHEEL
bolig_ping-1.6.1.dist-info/entry_points.txt
bolig_ping-1.6.1.dist-info/licenses/LICENSE
bolig_ping-1.6.1.dist-info/RECORD
