Metadata-Version: 2.4
Name: bolig_ping
Version: 1.6.1
Summary: Get a ping when your dream home becomes available.
Project-URL: Repository, https://github.com/saattrupdan/bolig_ping
Project-URL: Issues, https://github.com/saattrupdan/bolig_ping/issues
Author-email: Dan Saattrup Nielsen <saattrupdan@gmail.com>
Maintainer-email: Dan Saattrup Nielsen <saattrupdan@gmail.com>
License: MIT License
License-File: LICENSE
Requires-Python: <4.0,>=3.11
Requires-Dist: beautifulsoup4>=4.13.3
Requires-Dist: click>=8.1.8
Requires-Dist: pydantic>=2.10.6
Requires-Dist: python-dotenv>=1.0.1
Requires-Dist: requests>=2.32.3
Requires-Dist: tqdm>=4.67.1
Requires-Dist: yagmail>=0.15.293
